MultiTaxiLib/__init__.py
MultiTaxiLib/config.py
MultiTaxiLib/taxi_environment.py
MultiTaxiLib/taxi_utils/__init__.py
MultiTaxiLib/taxi_utils/actions_utils.py
MultiTaxiLib/taxi_utils/basic_utils.py
MultiTaxiLib/taxi_utils/observation_utils.py
MultiTaxiLib/taxi_utils/rendering_utils.py
MultiTaxiLib/taxi_utils/reward_utils.py
MultiTaxiLib/taxi_utils/termination_utils.py
MultiTaxiLib/visualizations/__init__.py
MultiTaxiLib/visualizations/streamlit_game.py
MultiTaxiLib-0.1.0.dist-info/METADATA
MultiTaxiLib-0.1.0.dist-info/WHEEL
MultiTaxiLib-0.1.0.dist-info/top_level.txt
MultiTaxiLib-0.1.0.dist-info/RECORD
