Metadata-Version: 2.1
Name: MultiTaxiLib
Version: 0.1.0
Summary: My short description for my project.
Home-page: https://github.com/ofirAbu/MultiTaxiLib/
Author: Ofir Abu
Author-email: ofir.abu@mail.huji.ac.il
License: MIT
Platform: UNKNOWN
Classifier: License :: OSI Approved :: MIT License
Classifier: Programming Language :: Python
Classifier: Programming Language :: Python :: 3
Classifier: Programming Language :: Python :: 3.6
Classifier: Programming Language :: Python :: Implementation :: CPython
Classifier: Programming Language :: Python :: Implementation :: PyPy
Requires-Python: >=3.6.0
Requires-Dist: numpy (>=1.10.4)
Requires-Dist: gym
Requires-Dist: ray
Requires-Dist: ray[rllib]
